{
	"category": "featuresets",
	"name": "ImagesWithText",
	"displayName": "Images with Text",
	"description": "Rows of images and text together",
	"inputs": {
		"text-header": "string",
		"list": [
			{
				"id": "string",
				"title": "string",
				"desc": "paragraph",
				"image": "image",
				"link": "link"
			}
		]
	},
	"defaults": {
		"text-header": "",
		"list": [
			{
				"id": "#ID#",
				"title": "",
				"desc": "string",
				"image": "",
				"link": ""
			},
			{
				"id": "#ID#",
				"title": "",
				"desc": "string",
				"image": "",
				"link": ""
			}
		]
	},
	"names": {
		"text-header": "Text Header",
		"list": "List",
		"id": "ID",
		"title": "Title",
		"desc": "Description",
		"image": "Image",
		"link": "Link"
	}
}
